{
  "model": "1gnn",
  "dataset": "mutag",
  "target_class": 1,
  "class_label": "Non-Mutagen",
  "num_samples": 100,
  "trainer_epoch": 299,
  "trainer_steps": 600,
  "total_generated": 100,
  "num_valid": 78,
  "validity_rate": 0.78,
  "mean_validation_score": 0.6811776026500926,
  "mean_valid_score": 0.8071331969773999,
  "mean_prediction_prob": 1.0,
  "mean_embedding_sim": 0.9354311865568161,
  "mean_degree_score": 0.49005592912780693,
  "mean_granularity": 0.0,
  "top_explanations": [
    {
      "rank": 1,
      "index": 62,
      "validation_score": 0.9841659214757585,
      "prediction_probability": 1.0,
      "num_nodes": 25,
      "num_edges": 28,
      "degree_score": 0.9994538143827879,
      "granularity": 0.0
    },
    {
      "rank": 2,
      "index": 97,
      "validation_score": 0.9824929682980201,
      "prediction_probability": 1.0,
      "num_nodes": 25,
      "num_edges": 28,
      "degree_score": 0.9994538143827879,
      "granularity": 0.0
    },
    {
      "rank": 3,
      "index": 30,
      "validation_score": 0.981543621831607,
      "prediction_probability": 1.0,
      "num_nodes": 26,
      "num_edges": 29,
      "degree_score": 0.9973365363925799,
      "granularity": 0.0
    },
    {
      "rank": 4,
      "index": 15,
      "validation_score": 0.9806269366366392,
      "prediction_probability": 1.0,
      "num_nodes": 26,
      "num_edges": 29,
      "degree_score": 0.9973365363925799,
      "granularity": 0.0
    },
    {
      "rank": 5,
      "index": 51,
      "validation_score": 0.9805612675631364,
      "prediction_probability": 1.0,
      "num_nodes": 25,
      "num_edges": 28,
      "degree_score": 0.9994538143827879,
      "granularity": 0.0
    },
    {
      "rank": 6,
      "index": 64,
      "validation_score": 0.9781984294968968,
      "prediction_probability": 1.0,
      "num_nodes": 24,
      "num_edges": 27,
      "degree_score": 0.9891097435172775,
      "granularity": 0.0
    },
    {
      "rank": 7,
      "index": 38,
      "validation_score": 0.976823778819566,
      "prediction_probability": 1.0,
      "num_nodes": 26,
      "num_edges": 29,
      "degree_score": 0.9973365363925799,
      "granularity": 0.0
    },
    {
      "rank": 8,
      "index": 33,
      "validation_score": 0.9764252054248309,
      "prediction_probability": 1.0,
      "num_nodes": 25,
      "num_edges": 28,
      "degree_score": 0.9994538143827879,
      "granularity": 0.0
    },
    {
      "rank": 9,
      "index": 58,
      "validation_score": 0.9757589465215147,
      "prediction_probability": 1.0,
      "num_nodes": 26,
      "num_edges": 29,
      "degree_score": 0.9973365363925799,
      "granularity": 0.0
    },
    {
      "rank": 10,
      "index": 84,
      "validation_score": 0.9754252799961746,
      "prediction_probability": 1.0,
      "num_nodes": 25,
      "num_edges": 28,
      "degree_score": 0.9994538143827879,
      "granularity": 0.0
    }
  ]
}